AUTHORS.rst
CHANGELOG.rst
MANIFEST.in
README.rst
setup.py
django_form_renderers.egg-info/PKG-INFO
django_form_renderers.egg-info/SOURCES.txt
django_form_renderers.egg-info/dependency_links.txt
django_form_renderers.egg-info/not-zip-safe
django_form_renderers.egg-info/requires.txt
django_form_renderers.egg-info/top_level.txt
form_renderers/__init__.py
form_renderers/__init__.pyc
form_renderers/models.py
form_renderers/models.pyc
form_renderers/monkey.py
form_renderers/monkey.pyc
form_renderers/tests/__init__.py
form_renderers/tests/__init__.pyc
form_renderers/tests/models.py
form_renderers/tests/models.pyc
form_renderers/tests/test_form.py
form_renderers/tests/test_form.pyc
form_renderers/tests/form_renderers/__init__.py
form_renderers/tests/form_renderers/__init__.pyc
form_renderers/tests/requirements/110.txt
form_renderers/tests/requirements/16.txt
form_renderers/tests/requirements/19.txt
form_renderers/tests/settings/110.py
form_renderers/tests/settings/110.pyc
form_renderers/tests/settings/111.pyc
form_renderers/tests/settings/16.py
form_renderers/tests/settings/16.pyc
form_renderers/tests/settings/19.py
form_renderers/tests/settings/19.pyc
form_renderers/tests/settings/__init__.py
form_renderers/tests/settings/__init__.pyc