Metadata-Version: 1.1
Name: django-form-renderers
Version: 0.3.2
Summary: Sometimes form.as_p doesn't cut it. This app adds more render methods to all forms. It also adds BEM style CSS classes to all form widgets and inputs.
Home-page: http://www.jmbo.org
Author: Praekelt Consulting
Author-email: dev@praekelt.com
License: BSD
Platform: UNKNOWN
Classifier: Programming Language :: Python
Classifier: License :: OSI Approved :: BSD License
Classifier: Development Status :: 5 - Production/Stable
Classifier: Operating System :: OS Independent
Classifier: Framework :: Django
Classifier: Intended Audience :: Developers
Classifier: Topic :: Internet :: WWW/HTTP :: Dynamic Content
